SOSAT/__init__.py
SOSAT/cli.py
SOSAT/stress_state.py
SOSAT/constraints/DITF_constraint.py
SOSAT/constraints/__init__.py
SOSAT/constraints/breakout_constraint.py
SOSAT/constraints/constraint_base.py
SOSAT/constraints/fault_constraint.py
SOSAT/constraints/faulting_regime_A_phi_constraint.py
SOSAT/constraints/faulting_regime_constraint.py
SOSAT/constraints/stress_measurement_constraint.py
SOSAT/risk_analysis/__init__.py
SOSAT/risk_analysis/critically_oriented_fault.py
SOSAT/risk_analysis/hydraulic_fracture.py
SOSAT/risk_analysis/user_prescribed_fault.py
SOSAT/samplers/__init__.py
SOSAT/samplers/rejection_sampler.py
SOSAT-0.7.2.dist-info/AUTHORS.rst
SOSAT-0.7.2.dist-info/LICENSE
SOSAT-0.7.2.dist-info/METADATA
SOSAT-0.7.2.dist-info/WHEEL
SOSAT-0.7.2.dist-info/entry_points.txt
SOSAT-0.7.2.dist-info/top_level.txt
SOSAT-0.7.2.dist-info/RECORD
