Metadata-Version: 2.1
Name: SOSAT
Version: 0.7.2
Summary: State of stress analysis tool
Home-page: https://github.com/pnnl/SOSAT
Author: Jeff Burghardt
Author-email: jeffrey.burghardt@pnnl.gov
License: BSD license
Keywords: SOSAT
Platform: UNKNOWN
Classifier: Development Status :: 2 - Pre-Alpha
Classifier: Intended Audience :: Developers
Classifier: License :: OSI Approved :: BSD License
Classifier: Natural Language :: English
Classifier: Programming Language :: Python :: 3
Classifier: Programming Language :: Python :: 3.7
Classifier: Programming Language :: Python :: 3.8
Requires-Python: >=3.6
Requires-Dist: Click >=7.0
Requires-Dist: numpy >=1.19
Requires-Dist: pint
Requires-Dist: scipy >=1.5
Requires-Dist: matplotlib
